cs_finix_server-0.1.5.dist-info/licenses/LICENSE
finix/__init__.py
finix/__main__.py
finix/portfolios-api.yaml
cs_finix_server-0.1.5.dist-info/METADATA
cs_finix_server-0.1.5.dist-info/WHEEL
cs_finix_server-0.1.5.dist-info/entry_points.txt
cs_finix_server-0.1.5.dist-info/top_level.txt
cs_finix_server-0.1.5.dist-info/RECORD
