Metadata-Version: 2.4
Name: cs-finix-server
Version: 0.1.5
Summary: A local Finix integration
Author-email: Rohith Menon <menonrohith1294@gmail.com>
License: MIT License
Requires-Python: >=3.11
License-File: LICENSE
Requires-Dist: httpx>=0.28.1
Requires-Dist: mcp[cli]>=1.5.0
Requires-Dist: pyyaml
Requires-Dist: requests
Dynamic: license-file
